{
	"name": "Users_csv",
	"properties": {
		"linkedServiceName": {
			"referenceName": "StackOverflow_blob",
			"type": "LinkedServiceReference"
		},
		"annotations": [],
		"type": "DelimitedText",
		"typeProperties": {
			"location": {
				"type": "AzureBlobStorageLocation",
				"fileName": "users.csv",
				"folderPath": "landing/users",
				"container": "sof-data"
			},
			"columnDelimiter": ",",
			"escapeChar": "\\",
			"firstRowAsHeader": true,
			"quoteChar": "\""
		},
		"schema": []
	},
	"type": "Microsoft.DataFactory/factories/datasets"
}